setup.py
elog/__init__.py
elog/handlers.py
elog/records.py
elog.egg-info/PKG-INFO
elog.egg-info/SOURCES.txt
elog.egg-info/dependency_links.txt
elog.egg-info/requires.txt
elog.egg-info/top_level.txt
test/test_main.py