Metadata-Version: 1.1
Name: elog
Version: 1.0-alpha-20141117-2328-52e913a
Summary: ElasticSearch logging handler and tools
Home-page: https://github.com/yandex-sysmon/elog
Author: Devaev Maxim
Author-email: mdevaev@gmail.com
License: LGPLv3
Platform: any
Classifier: Development Status :: 2 - Pre-Alpha
Classifier: License :: OSI Approved :: GNU Lesser General Public License v3 (LGPLv3)
Classifier: Operating System :: OS Independent
Classifier: Programming Language :: Python :: 3
Classifier: Topic :: Software Development :: Libraries :: Python Modules
Classifier: Topic :: System :: Networking :: Monitoring
Classifier: Topic :: System :: Logging
